{"strategy":{"UniversalMACD":{"trades":[{"pair":"ETH/USDT","stake_amount":197.909861,"max_stake_amount":197.909861,"amount":0.1307,"open_date":"2023-01-18 16:35:00+00:00","close_date":"2023-01-18 19:20:00+00:00","open_rate":1514.23,"close_rate":1542.85,"fee_open":0.001,"fee_close":0.001,"trade_duration":165,"profit_ratio":0.016864929757572332,"profit_abs":3.34107364,"exit_reason":"roi","initial_stop_loss_abs":1032.71,"initial_stop_loss_ratio":-0.318,"stop_loss_abs":1032.71,"stop_loss_ratio":-0.318,"min_rate":1501.85,"max_rate":1566.88,"is_open":false,"enter_tag":null,"leverage":1.0,"is_short":false,"open_timestamp":1674059700000,"close_timestamp":1674069600000,"orders":[{"amount":0.1307,"safe_price":1514.23,"ft_order_side":"buy","order_filled_timestamp":1674059700000,"ft_is_entry":true},{"amount":0.1307,"safe_price":1542.85,"ft_order_side":"sell","order_filled_timestamp":1674069600000,"ft_is_entry":false}]},{"pair":"ETH/USDT","stake_amount":198.583476,"max_stake_amount":198.583476,"amount":0.1274,"open_date":"2023-03-03 01:50:00+00:00","close_date":"2023-03-03 04:35:00+00:00","open_rate":1558.74,"close_rate":1567.45,"fee_open":0.001,"fee_close":0.001,"trade_duration":165,"profit_ratio":0.0035786800472599406,"profit_abs":0.71137739,"exit_reason":"roi","initial_stop_loss_abs":1063.07,"initial_stop_loss_ratio":-0.318,"stop_loss_abs":1063.07,"stop_loss_ratio":-0.318,"min_rate":1544.39,"max_rate":1570.34,"is_open":false,"enter_tag":null,"leverage":1.0,"is_short":false,"open_timestamp":1677808200000,"close_timestamp":1677818100000,"orders":[{"amount":0.1274,"safe_price":1558.74,"ft_order_side":"buy","order_filled_timestamp":1677808200000,"ft_is_entry":true},{"amount":0.1274,"safe_price":1567.45,"ft_order_side":"sell","order_filled_timestamp":1677818100000,"ft_is_entry":false}]},{"pair":"ETH/USDT","stake_amount":198.76535,"max_stake_amount":198.76535,"amount":0.1405,"open_date":"2023-03-09 21:00:00+00:00","close_date":"2023-03-09 23:45:00+00:00","open_rate":1414.7,"close_rate":1436.07,"fee_open":0.001,"fee_close":0.001,"trade_duration":165,"profit_ratio":0.013077492971146468,"profit_abs":2.60195182,"exit_reason":"roi","initial_stop_loss_abs":964.83,"initial_stop_loss_ratio":-0.318,"stop_loss_abs":964.83,"stop_loss_ratio":-0.318,"min_rate":1414.49,"max_rate":1448.22,"is_open":false,"enter_tag":null,"leverage":1.0,"is_short":false,"open_timestamp":1678395600000,"close_timestamp":1678405500000,"orders":[{"amount":0.1405,"safe_price":1414.7,"ft_order_side":"buy","order_filled_timestamp":1678395600000,"ft_is_entry":true},{"amount":0.1405,"safe_price":1436.07,"ft_order_side":"sell","order_filled_timestamp":1678405500000,"ft_is_entry":false}]},{"pair":"ETH/USDT","stake_amount":199.17255,"max_stake_amount":199.17255,"amount":0.1002,"open_date":"2023-04-19 08:50:00+00:00","close_date":"2023-04-19 14:00:00+00:00","open_rate":1987.75,"close_rate":1991.7294794794793,"fee_open":0.001,"fee_close":0.001,"trade_duration":310,"profit_ratio":0.0,"profit_abs":0.0,"exit_reason":"roi","initial_stop_loss_abs":1355.65,"initial_stop_loss_ratio":-0.318,"stop_loss_abs":1355.65,"stop_loss_ratio":-0.318,"min_rate":1962.06,"max_rate":1994.0,"is_open":false,"enter_tag":null,"leverage":1.0,"is_short":false,"open_timestamp":1681894200000,"close_timestamp":1681912800000,"orders":[{"amount":0.1002,"safe_price":1987.75,"ft_order_side":"buy","order_filled_timestamp":1681894200000,"ft_is_entry":true},{"amount":0.1002,"safe_price":1991.7294794794793,"ft_order_side":"sell","order_filled_timestamp":1681912800000,"ft_is_entry":false}]},{"pair":"ETH/USDT","stake_amount":199.18647,"max_stake_amount":199.18647,"amount":0.1085,"open_date":"2023-04-26 19:50:00+00:00","close_date":"2023-04-26 22:35:00+00:00","open_rate":1835.82,"close_rate":1856.4,"fee_open":0.001,"fee_close":0.001,"trade_duration":165,"profit_ratio":0.009189849272210289,"profit_abs":1.83232413,"exit_reason":"roi","initial_stop_loss_abs":1252.03,"initial_stop_loss_ratio":-0.318,"stop_loss_abs":1252.03,"stop_loss_ratio":-0.318,"min_rate":1785.0,"max_rate":1883.37,"is_open":false,"enter_tag":null,"leverage":1.0,"is_short":false,"open_timestamp":1682538600000,"close_timestamp":1682548500000,"orders":[{"amount":0.1085,"safe_price":1835.82,"ft_order_side":"buy","order_filled_timestamp":1682538600000,"ft_is_entry":true},{"amount":0.1085,"safe_price":1856.4,"ft_order_side":"sell","order_filled_timestamp":1682548500000,"ft_is_entry":false}]},{"pair":"ETH/USDT","stake_amount":199.523944,"max_stake_amount":199.523944,"amount":0.1213,"open_date":"2023-06-14 20:50:00+00:00","close_date":"2023-06-14 23:35:00+00:00","open_rate":1644.88,"close_rate":1649.42,"fee_open":0.001,"fee_close":0.001,"trade_duration":165,"profit_ratio":0.0007565631197750258,"profit_abs":0.15110341,"exit_reason":"roi","initial_stop_loss_abs":1121.81,"initial_stop_loss_ratio":-0.318,"stop_loss_abs":1121.81,"stop_loss_ratio":-0.318,"min_rate":1630.43,"max_rate":1656.0,"is_open":false,"enter_tag":null,"leverage":1.0,"is_short":false,"open_timestamp":1686775800000,"close_timestamp":1686785700000,"orders":[{"amount":0.1213,"safe_price":1644.88,"ft_order_side":"buy","order_filled_timestamp":1686775800000,"ft_is_entry":true},{"amount":0.1213,"safe_price":1649.42,"ft_order_side":"sell","order_filled_timestamp":1686785700000,"ft_is_entry":false}]},{"pair":"ETH/USDT","stake_amount":199.616802,"max_stake_amount":199.616802,"amount":0.1218,"open_date":"2023-08-17 22:40:00+00:00","close_date":"2023-08-17 23:40:00+00:00","open_rate":1638.89,"close_rate":1691.3869769769767,"fee_open":0.001,"fee_close":0.001,"trade_duration":60,"profit_ratio":0.029970029970029975,"profit_abs":5.98850406,"exit_reason":"roi","initial_stop_loss_abs":1117.73,"initial_stop_loss_ratio":-0.318,"stop_loss_abs":1117.73,"stop_loss_ratio":-0.318,"min_rate":1636.42,"max_rate":1717.69,"is_open":false,"enter_tag":null,"leverage":1.0,"is_short":false,"open_timestamp":1692312000000,"close_timestamp":1692315600000,"orders":[{"amount":0.1218,"safe_price":1638.89,"ft_order_side":"buy","order_filled_timestamp":1692312000000,"ft_is_entry":true},{"amount":0.1218,"safe_price":1691.3869769769767,"ft_order_side":"sell","order_filled_timestamp":1692315600000,"ft_is_entry":false}]}],"locks":[],"best_pair":{"key":"ETH/USDT","trades":7,"profit_mean":0.010491077876856289,"profit_mean_pct":1.049107787685629,"profit_sum":0.07343754513799403,"profit_sum_pct":7.34,"profit_total_abs":14.62633445,"profit_total":0.01462633445,"profit_total_pct":1.46,"duration_avg":"2:51:00","wins":6,"draws":1,"losses":0,"winrate":0.8571428571428571},"worst_pair":{"key":"ETH/USDT","trades":7,"profit_mean":0.010491077876856289,"profit_mean_pct":1.049107787685629,"profit_sum":0.07343754513799403,"profit_sum_pct":7.34,"profit_total_abs":14.62633445,"profit_total":0.01462633445,"profit_total_pct":1.46,"duration_avg":"2:51:00","wins":6,"draws":1,"losses":0,"winrate":0.8571428571428571},"results_per_pair":[{"key":"ETH/USDT","trades":7,"profit_mean":0.010491077876856289,"profit_mean_pct":1.049107787685629,"profit_sum":0.07343754513799403,"profit_sum_pct":7.34,"profit_total_abs":14.62633445,"profit_total":0.01462633445,"profit_total_pct":1.46,"duration_avg":"2:51:00","wins":6,"draws":1,"losses":0,"winrate":0.8571428571428571},{"key":"TOTAL","trades":7,"profit_mean":0.010491077876856289,"profit_mean_pct":1.049107787685629,"profit_sum":0.07343754513799403,"profit_sum_pct":7.34,"profit_total_abs":14.62633445,"profit_total":0.01462633445,"profit_total_pct":1.46,"duration_avg":"2:51:00","wins":6,"draws":1,"losses":0,"winrate":0.8571428571428571}],"results_per_enter_tag":[{"key":"TOTAL","trades":7,"profit_mean":0.010491077876856289,"profit_mean_pct":1.049107787685629,"profit_sum":0.07343754513799403,"profit_sum_pct":7.34,"profit_total_abs":14.62633445,"profit_total":0.01462633445,"profit_total_pct":1.46,"duration_avg":"2:51:00","wins":6,"draws":1,"losses":0,"winrate":0.8571428571428571}],"exit_reason_summary":[{"exit_reason":"roi","trades":7,"wins":6,"draws":1,"losses":0,"winrate":0.8571428571428571,"profit_mean":0.010491077876856289,"profit_mean_pct":1.05,"profit_sum":0.07343754513799403,"profit_sum_pct":7.34,"profit_total_abs":14.62633445,"profit_total":0.07343754513799403,"profit_total_pct":7.34}],"left_open_trades":[{"key":"TOTAL","trades":0,"profit_mean":0.0,"profit_mean_pct":0.0,"profit_sum":0.0,"profit_sum_pct":0.0,"profit_total_abs":0.0,"profit_total":0.0,"profit_total_pct":0.0,"duration_avg":"0:00","wins":0,"draws":0,"losses":0,"winrate":0.0}],"total_trades":7,"trade_count_long":7,"trade_count_short":0,"total_volume":1392.758453,"avg_stake_amount":198.96549328571427,"profit_mean":0.010491077876856289,"profit_median":0.009189849272210289,"profit_total":0.01462633445,"profit_total_long":0.01462633445,"profit_total_short":0.0,"profit_total_abs":14.62633445,"profit_total_long_abs":14.62633445,"profit_total_short_abs":0.0,"cagr":0.017586894279532306,"expectancy":2.08947635,"expectancy_ratio":100,"sortino":-100,"sharpe":0.4669950673714967,"calmar":-100,"profit_factor":0.0,"backtest_start":"2023-01-01 00:00:00","backtest_start_ts":1672531200000,"backtest_end":"2023-11-01 00:00:00","backtest_end_ts":1698796800000,"backtest_days":304,"backtest_run_start_ts":1699774445,"backtest_run_end_ts":1699774446,"trades_per_day":0.02,"market_change":0.5095502156500308,"pairlist":["ETH/USDT"],"stake_amount":"unlimited","stake_currency":"USDT","stake_currency_decimals":3,"starting_balance":1000,"dry_run_wallet":1000,"final_balance":1014.62633445,"rejected_signals":0,"timedout_entry_orders":0,"timedout_exit_orders":0,"canceled_trade_entries":0,"canceled_entry_orders":0,"replaced_entry_orders":0,"max_open_trades":1,"max_open_trades_setting":5,"timeframe":"5m","timeframe_detail":"","timerange":"20230101-20231101","enable_protections":false,"strategy_name":"UniversalMACD","stoploss":-0.318,"trailing_stop":false,"trailing_stop_positive":null,"trailing_stop_positive_offset":0.0,"trailing_only_offset_is_reached":false,"use_custom_stoploss":false,"minimal_roi":{"0":0.213,"27":0.099,"60":0.03,"164":0},"use_exit_signal":true,"exit_profit_only":false,"exit_profit_offset":0.0,"ignore_roi_if_entry_signal":false,"periodic_breakdown":{"day":[{"date":"18/01/2023","date_ts":1674000000000,"profit_abs":3.34107364,"wins":1,"draws":0,"loses":0,"winrate":1.0},{"date":"19/01/2023","date_ts":1674086400000,"profit_abs":0.0,"wins":0,"draws":0,"loses":0,"winrate":0.0},{"date":"20/01/2023","date_ts":1674172800000,"profit_abs":0.0,"wins":0,"draws":0,"loses":0,"winrate":0.0},{"date":"21/01/2023","date_ts":1674259200000,"profit_abs":0.0,"wins":0,"draws":0,"loses":0,"winrate":0.0},{"date":"22/01/2023","date_ts":1674345600000,"profit_abs":0.0,"wins":0,"draws":0,"loses":0,"winrate":0.0},{"date":"23/01/2023","date_ts":1674432000000,"profit_abs":0.0,"wins":0,"draws":0,"loses":0,"winrate":0.0},{"date":"24/01/2023","date_ts":1674518400000,"profit_abs":0.0,"wins":0,"draws":0,"loses":0,"winrate":0.0},{"date":"25/01/2023","date_ts":1674604800000,"profit_abs":0.0,"wins":0,"draws":0,"loses":0,"winrate":0.0},{"date":"26/01/2023","date_ts":1674691200000,"profit_abs":0.0,"wins":0,"draws":0,"loses":0,"winrate":0.0},{"date":"27/01/2023","date_ts":1674777600000,"profit_abs":0.0,"wins":0,"draws":0,"loses":0,"winrate":0.0},{"date":"28/01/2023","date_ts":1674864000000,"profit_abs":0.0,"wins":0,"draws":0,"loses":0,"winrate":0.0},{"date":"29/01/2023","date_ts":1674950400000,"profit_abs":0.0,"wins":0,"draws":0,"loses":0,"winrate":0.0},{"date":"30/01/2023","date_ts":1675036800000,"profit_abs":0.0,"wins":0,"draws":0,"loses":0,"winrate":0.0},{"date":"31/01/2023","date_ts":1675123200000,"profit_abs":0.0,"wins":0,"draws":0,"loses":0,"winrate":0.0},{"date":"01/02/2023","date_ts":1675209600000,"profit_abs":0.0,"wins":0,"draws":0,"loses":0,"winrate":0.0},{"date":"02/02/2023","date_ts":1675296000000,"profit_abs":0.0,"wins":0,"draws":0,"loses":0,"winrate":0.0},{"date":"03/02/2023","date_ts":1675382400000,"profit_abs":0.0,"wins":0,"draws":0,"loses":0,"winrate":0.0},{"date":"04/02/2023","date_ts":1675468800000,"profit_abs":0.0,"wins":0,"draws":0,"loses":0,"winrate":0.0},{"date":"05/02/2023","date_ts":1675555200000,"profit_abs":0.0,"wins":0,"draws":0,"loses":0,"winrate":0.0},{"date":"06/02/2023","date_ts":1675641600000,"profit_abs":0.0,"wins":0,"draws":0,"loses":0,"winrate":0.0},{"date":"07/02/2023","date_ts":1675728000000,"profit_abs":0.0,"wins":0,"draws":0,"loses":0,"winrate":0.0},{"date":"08/02/2023","date_ts":1675814400000,"profit_abs":0.0,"wins":0,"draws":0,"loses":0,"winrate":0.0},{"date":"09/02/2023","date_ts":1675900800000,"profit_abs":0.0,"wins":0,"draws":0,"loses":0,"winrate":0.0},{"date":"10/02/2023","date_ts":1675987200000,"profit_abs":0.0,"wins":0,"draws":0,"loses":0,"winrate":0.0},{"date":"11/02/2023","date_ts":1676073600000,"profit_abs":0.0,"wins":0,"draws":0,"loses":0,"winrate":0.0},{"date":"12/02/2023","date_ts":1676160000000,"profit_abs":0.0,"wins":0,"draws":0,"loses":0,"winrate":0.0},{"date":"13/02/2023","date_ts":1676246400000,"profit_abs":0.0,"wins":0,"draws":0,"loses":0,"winrate":0.0},{"date":"14/02/2023","date_ts":1676332800000,"profit_abs":0.0,"wins":0,"draws":0,"loses":0,"winrate":0.0},{"date":"15/02/2023","date_ts":1676419200000,"profit_abs":0.0,"wins":0,"draws":0,"loses":0,"winrate":0.0},{"date":"16/02/2023","date_ts":1676505600000,"profit_abs":0.0,"wins":0,"draws":0,"loses":0,"winrate":0.0},{"date":"17/02/2023","date_ts":1676592000000,"profit_abs":0.0,"wins":0,"draws":0,"loses":0,"winrate":0.0},{"date":"18/02/2023","date_ts":1676678400000,"profit_abs":0.0,"wins":0,"draws":0,"loses":0,"winrate":0.0},{"date":"19/02/2023","date_ts":1676764800000,"profit_abs":0.0,"wins":0,"draws":0,"loses":0,"winrate":0.0},{"date":"20/02/2023","date_ts":1676851200000,"profit_abs":0.0,"wins":0,"draws":0,"loses":0,"winrate":0.0},{"date":"21/02/2023","date_ts":1676937600000,"profit_abs":0.0,"wins":0,"draws":0,"loses":0,"winrate":0.0},{"date":"22/02/2023","date_ts":1677024000000,"profit_abs":0.0,"wins":0,"draws":0,"loses":0,"winrate":0.0},{"date":"23/02/2023","date_ts":1677110400000,"profit_abs":0.0,"wins":0,"draws":0,"loses":0,"winrate":0.0},{"date":"24/02/2023","date_ts":1677196800000,"profit_abs":0.0,"wins":0,"draws":0,"loses":0,"winrate":0.0},{"date":"25/02/2023","date_ts":1677283200000,"profit_abs":0.0,"wins":0,"draws":0,"loses":0,"winrate":0.0},{"date":"26/02/2023","date_ts":1677369600000,"profit_abs":0.0,"wins":0,"draws":0,"loses":0,"winrate":0.0},{"date":"27/02/2023","date_ts":1677456000000,"profit_abs":0.0,"wins":0,"draws":0,"loses":0,"winrate":0.0},{"date":"28/02/2023","date_ts":1677542400000,"profit_abs":0.0,"wins":0,"draws":0,"loses":0,"winrate":0.0},{"date":"01/03/2023","date_ts":1677628800000,"profit_abs":0.0,"wins":0,"draws":0,"loses":0,"winrate":0.0},{"date":"02/03/2023","date_ts":1677715200000,"profit_abs":0.0,"wins":0,"draws":0,"loses":0,"winrate":0.0},{"date":"03/03/2023","date_ts":1677801600000,"profit_abs":0.71137739,"wins":1,"draws":0,"loses":0,"winrate":1.0},{"date":"04/03/2023","date_ts":1677888000000,"profit_abs":0.0,"wins":0,"draws":0,"loses":0,"winrate":0.0},{"date":"05/03/2023","date_ts":1677974400000,"profit_abs":0.0,"wins":0,"draws":0,"loses":0,"winrate":0.0},{"date":"06/03/2023","date_ts":1678060800000,"profit_abs":0.0,"wins":0,"draws":0,"loses":0,"winrate":0.0},{"date":"07/03/2023","date_ts":1678147200000,"profit_abs":0.0,"wins":0,"draws":0,"loses":0,"winrate":0.0},{"date":"08/03/2023","date_ts":1678233600000,"profit_abs":0.0,"wins":0,"draws":0,"loses":0,"winrate":0.0},{"date":"09/03/2023","date_ts":1678320000000,"profit_abs":2.60195182,"wins":1,"draws":0,"loses":0,"winrate":1.0},{"date":"10/03/2023","date_ts":1678406400000,"profit_abs":0.0,"wins":0,"draws":0,"loses":0,"winrate":0.0},{"date":"11/03/2023","date_ts":1678492800000,"profit_abs":0.0,"wins":0,"draws":0,"loses":0,"winrate":0.0},{"date":"12/03/2023","date_ts":1678579200000,"profit_abs":0.0,"wins":0,"draws":0,"loses":0,"winrate":0.0},{"date":"13/03/2023","date_ts":1678665600000,"profit_abs":0.0,"wins":0,"draws":0,"loses":0,"winrate":0.0},{"date":"14/03/2023","date_ts":1678752000000,"profit_abs":0.0,"wins":0,"draws":0,"loses":0,"winrate":0.0},{"date":"15/03/2023","date_ts":1678838400000,"profit_abs":0.0,"wins":0,"draws":0,"loses":0,"winrate":0.0},{"date":"16/03/2023","date_ts":1678924800000,"profit_abs":0.0,"wins":0,"draws":0,"loses":0,"winrate":0.0},{"date":"17/03/2023","date_ts":1679011200000,"profit_abs":0.0,"wins":0,"draws":0,"loses":0,"winrate":0.0},{"date":"18/03/2023","date_ts":1679097600000,"profit_abs":0.0,"wins":0,"draws":0,"loses":0,"winrate":0.0},{"date":"19/03/2023","date_ts":1679184000000,"profit_abs":0.0,"wins":0,"draws":0,"loses":0,"winrate":0.0},{"date":"20/03/2023","date_ts":1679270400000,"profit_abs":0.0,"wins":0,"draws":0,"loses":0,"winrate":0.0},{"date":"21/03/2023","date_ts":1679356800000,"profit_abs":0.0,"wins":0,"draws":0,"loses":0,"winrate":0.0},{"date":"22/03/2023","date_ts":1679443200000,"profit_abs":0.0,"wins":0,"draws":0,"loses":0,"winrate":0.0},{"date":"23/03/2023","date_ts":1679529600000,"profit_abs":0.0,"wins":0,"draws":0,"loses":0,"winrate":0.0},{"date":"24/03/2023","date_ts":1679616000000,"profit_abs":0.0,"wins":0,"draws":0,"loses":0,"winrate":0.0},{"date":"25/03/2023","date_ts":1679702400000,"profit_abs":0.0,"wins":0,"draws":0,"loses":0,"winrate":0.0},{"date":"26/03/2023","date_ts":1679788800000,"profit_abs":0.0,"wins":0,"draws":0,"loses":0,"winrate":0.0},{"date":"27/03/2023","date_ts":1679875200000,"profit_abs":0.0,"wins":0,"draws":0,"loses":0,"winrate":0.0},{"date":"28/03/2023","date_ts":1679961600000,"profit_abs":0.0,"wins":0,"draws":0,"loses":0,"winrate":0.0},{"date":"29/03/2023","date_ts":1680048000000,"profit_abs":0.0,"wins":0,"draws":0,"loses":0,"winrate":0.0},{"date":"30/03/2023","date_ts":1680134400000,"profit_abs":0.0,"wins":0,"draws":0,"loses":0,"winrate":0.0},{"date":"31/03/2023","date_ts":1680220800000,"profit_abs":0.0,"wins":0,"draws":0,"loses":0,"winrate":0.0},{"date":"01/04/2023","date_ts":1680307200000,"profit_abs":0.0,"wins":0,"draws":0,"loses":0,"winrate":0.0},{"date":"02/04/2023","date_ts":1680393600000,"profit_abs":0.0,"wins":0,"draws":0,"loses":0,"winrate":0.0},{"date":"03/04/2023","date_ts":1680480000000,"profit_abs":0.0,"wins":0,"draws":0,"loses":0,"winrate":0.0},{"date":"04/04/2023","date_ts":1680566400000,"profit_abs":0.0,"wins":0,"draws":0,"loses":0,"winrate":0.0},{"date":"05/04/2023","date_ts":1680652800000,"profit_abs":0.0,"wins":0,"draws":0,"loses":0,"winrate":0.0},{"date":"06/04/2023","date_ts":1680739200000,"profit_abs":0.0,"wins":0,"draws":0,"loses":0,"winrate":0.0},{"date":"07/04/2023","date_ts":1680825600000,"profit_abs":0.0,"wins":0,"draws":0,"loses":0,"winrate":0.0},{"date":"08/04/2023","date_ts":1680912000000,"profit_abs":0.0,"wins":0,"draws":0,"loses":0,"winrate":0.0},{"date":"09/04/2023","date_ts":1680998400000,"profit_abs":0.0,"wins":0,"draws":0,"loses":0,"winrate":0.0},{"date":"10/04/2023","date_ts":1681084800000,"profit_abs":0.0,"wins":0,"draws":0,"loses":0,"winrate":0.0},{"date":"11/04/2023","date_ts":1681171200000,"profit_abs":0.0,"wins":0,"draws":0,"loses":0,"winrate":0.0},{"date":"12/04/2023","date_ts":1681257600000,"profit_abs":0.0,"wins":0,"draws":0,"loses":0,"winrate":0.0},{"date":"13/04/2023","date_ts":1681344000000,"profit_abs":0.0,"wins":0,"draws":0,"loses":0,"winrate":0.0},{"date":"14/04/2023","date_ts":1681430400000,"profit_abs":0.0,"wins":0,"draws":0,"loses":0,"winrate":0.0},{"date":"15/04/2023","date_ts":1681516800000,"profit_abs":0.0,"wins":0,"draws":0,"loses":0,"winrate":0.0},{"date":"16/04/2023","date_ts":1681603200000,"profit_abs":0.0,"wins":0,"draws":0,"loses":0,"winrate":0.0},{"date":"17/04/2023","date_ts":1681689600000,"profit_abs":0.0,"wins":0,"draws":0,"loses":0,"winrate":0.0},{"date":"18/04/2023","date_ts":1681776000000,"profit_abs":0.0,"wins":0,"draws":0,"loses":0,"winrate":0.0},{"date":"19/04/2023","date_ts":1681862400000,"profit_abs":0.0,"wins":0,"draws":1,"loses":0,"winrate":0.0},{"date":"20/04/2023","date_ts":1681948800000,"profit_abs":0.0,"wins":0,"draws":0,"loses":0,"winrate":0.0},{"date":"21/04/2023","date_ts":1682035200000,"profit_abs":0.0,"wins":0,"draws":0,"loses":0,"winrate":0.0},{"date":"22/04/2023","date_ts":1682121600000,"profit_abs":0.0,"wins":0,"draws":0,"loses":0,"winrate":0.0},{"date":"23/04/2023","date_ts":1682208000000,"profit_abs":0.0,"wins":0,"draws":0,"loses":0,"winrate":0.0},{"date":"24/04/2023","date_ts":1682294400000,"profit_abs":0.0,"wins":0,"draws":0,"loses":0,"winrate":0.0},{"date":"25/04/2023","date_ts":1682380800000,"profit_abs":0.0,"wins":0,"draws":0,"loses":0,"winrate":0.0},{"date":"26/04/2023","date_ts":1682467200000,"profit_abs":1.83232413,"wins":1,"draws":0,"loses":0,"winrate":1.0},{"date":"27/04/2023","date_ts":1682553600000,"profit_abs":0.0,"wins":0,"draws":0,"loses":0,"winrate":0.0},{"date":"28/04/2023","date_ts":1682640000000,"profit_abs":0.0,"wins":0,"draws":0,"loses":0,"winrate":0.0},{"date":"29/04/2023","date_ts":1682726400000,"profit_abs":0.0,"wins":0,"draws":0,"loses":0,"winrate":0.0},{"date":"30/04/2023","date_ts":1682812800000,"profit_abs":0.0,"wins":0,"draws":0,"loses":0,"winrate":0.0},{"date":"01/05/2023","date_ts":1682899200000,"profit_abs":0.0,"wins":0,"draws":0,"loses":0,"winrate":0.0},{"date":"02/05/2023","date_ts":1682985600000,"profit_abs":0.0,"wins":0,"draws":0,"loses":0,"winrate":0.0},{"date":"03/05/2023","date_ts":1683072000000,"profit_abs":0.0,"wins":0,"draws":0,"loses":0,"winrate":0.0},{"date":"04/05/2023","date_ts":1683158400000,"profit_abs":0.0,"wins":0,"draws":0,"loses":0,"winrate":0.0},{"date":"05/05/2023","date_ts":1683244800000,"profit_abs":0.0,"wins":0,"draws":0,"loses":0,"winrate":0.0},{"date":"06/05/2023","date_ts":1683331200000,"profit_abs":0.0,"wins":0,"draws":0,"loses":0,"winrate":0.0},{"date":"07/05/2023","date_ts":1683417600000,"profit_abs":0.0,"wins":0,"draws":0,"loses":0,"winrate":0.0},{"date":"08/05/2023","date_ts":1683504000000,"profit_abs":0.0,"wins":0,"draws":0,"loses":0,"winrate":0.0},{"date":"09/05/2023","date_ts":1683590400000,"profit_abs":0.0,"wins":0,"draws":0,"loses":0,"winrate":0.0},{"date":"10/05/2023","date_ts":1683676800000,"profit_abs":0.0,"wins":0,"draws":0,"loses":0,"winrate":0.0},{"date":"11/05/2023","date_ts":1683763200000,"profit_abs":0.0,"wins":0,"draws":0,"loses":0,"winrate":0.0},{"date":"12/05/2023","date_ts":1683849600000,"profit_abs":0.0,"wins":0,"draws":0,"loses":0,"winrate":0.0},{"date":"13/05/2023","date_ts":1683936000000,"profit_abs":0.0,"wins":0,"draws":0,"loses":0,"winrate":0.0},{"date":"14/05/2023","date_ts":1684022400000,"profit_abs":0.0,"wins":0,"draws":0,"loses":0,"winrate":0.0},{"date":"15/05/2023","date_ts":1684108800000,"profit_abs":0.0,"wins":0,"draws":0,"loses":0,"winrate":0.0},{"date":"16/05/2023","date_ts":1684195200000,"profit_abs":0.0,"wins":0,"draws":0,"loses":0,"winrate":0.0},{"date":"17/05/2023","date_ts":1684281600000,"profit_abs":0.0,"wins":0,"draws":0,"loses":0,"winrate":0.0},{"date":"18/05/2023","date_ts":1684368000000,"profit_abs":0.0,"wins":0,"draws":0,"loses":0,"winrate":0.0},{"date":"19/05/2023","date_ts":1684454400000,"profit_abs":0.0,"wins":0,"draws":0,"loses":0,"winrate":0.0},{"date":"20/05/2023","date_ts":1684540800000,"profit_abs":0.0,"wins":0,"draws":0,"loses":0,"winrate":0.0},{"date":"21/05/2023","date_ts":1684627200000,"profit_abs":0.0,"wins":0,"draws":0,"loses":0,"winrate":0.0},{"date":"22/05/2023","date_ts":1684713600000,"profit_abs":0.0,"wins":0,"draws":0,"loses":0,"winrate":0.0},{"date":"23/05/2023","date_ts":1684800000000,"profit_abs":0.0,"wins":0,"draws":0,"loses":0,"winrate":0.0},{"date":"24/05/2023","date_ts":1684886400000,"profit_abs":0.0,"wins":0,"draws":0,"loses":0,"winrate":0.0},{"date":"25/05/2023","date_ts":1684972800000,"profit_abs":0.0,"wins":0,"draws":0,"loses":0,"winrate":0.0},{"date":"26/05/2023","date_ts":1685059200000,"profit_abs":0.0,"wins":0,"draws":0,"loses":0,"winrate":0.0},{"date":"27/05/2023","date_ts":1685145600000,"profit_abs":0.0,"wins":0,"draws":0,"loses":0,"winrate":0.0},{"date":"28/05/2023","date_ts":1685232000000,"profit_abs":0.0,"wins":0,"draws":0,"loses":0,"winrate":0.0},{"date":"29/05/2023","date_ts":1685318400000,"profit_abs":0.0,"wins":0,"draws":0,"loses":0,"winrate":0.0},{"date":"30/05/2023","date_ts":1685404800000,"profit_abs":0.0,"wins":0,"draws":0,"loses":0,"winrate":0.0},{"date":"31/05/2023","date_ts":1685491200000,"profit_abs":0.0,"wins":0,"draws":0,"loses":0,"winrate":0.0},{"date":"01/06/2023","date_ts":1685577600000,"profit_abs":0.0,"wins":0,"draws":0,"loses":0,"winrate":0.0},{"date":"02/06/2023","date_ts":1685664000000,"profit_abs":0.0,"wins":0,"draws":0,"loses":0,"winrate":0.0},{"date":"03/06/2023","date_ts":1685750400000,"profit_abs":0.0,"wins":0,"draws":0,"loses":0,"winrate":0.0},{"date":"04/06/2023","date_ts":1685836800000,"profit_abs":0.0,"wins":0,"draws":0,"loses":0,"winrate":0.0},{"date":"05/06/2023","date_ts":1685923200000,"profit_abs":0.0,"wins":0,"draws":0,"loses":0,"winrate":0.0},{"date":"06/06/2023","date_ts":1686009600000,"profit_abs":0.0,"wins":0,"draws":0,"loses":0,"winrate":0.0},{"date":"07/06/2023","date_ts":1686096000000,"profit_abs":0.0,"wins":0,"draws":0,"loses":0,"winrate":0.0},{"date":"08/06/2023","date_ts":1686182400000,"profit_abs":0.0,"wins":0,"draws":0,"loses":0,"winrate":0.0},{"date":"09/06/2023","date_ts":1686268800000,"profit_abs":0.0,"wins":0,"draws":0,"loses":0,"winrate":0.0},{"date":"10/06/2023","date_ts":1686355200000,"profit_abs":0.0,"wins":0,"draws":0,"loses":0,"winrate":0.0},{"date":"11/06/2023","date_ts":1686441600000,"profit_abs":0.0,"wins":0,"draws":0,"loses":0,"winrate":0.0},{"date":"12/06/2023","date_ts":1686528000000,"profit_abs":0.0,"wins":0,"draws":0,"loses":0,"winrate":0.0},{"date":"13/06/2023","date_ts":1686614400000,"profit_abs":0.0,"wins":0,"draws":0,"loses":0,"winrate":0.0},{"date":"14/06/2023","date_ts":1686700800000,"profit_abs":0.15110341,"wins":1,"draws":0,"loses":0,"winrate":1.0},{"date":"15/06/2023","date_ts":1686787200000,"profit_abs":0.0,"wins":0,"draws":0,"loses":0,"winrate":0.0},{"date":"16/06/2023","date_ts":1686873600000,"profit_abs":0.0,"wins":0,"draws":0,"loses":0,"winrate":0.0},{"date":"17/06/2023","date_ts":1686960000000,"profit_abs":0.0,"wins":0,"draws":0,"loses":0,"winrate":0.0},{"date":"18/06/2023","date_ts":1687046400000,"profit_abs":0.0,"wins":0,"draws":0,"loses":0,"winrate":0.0},{"date":"19/06/2023","date_ts":1687132800000,"profit_abs":0.0,"wins":0,"draws":0,"loses":0,"winrate":0.0},{"date":"20/06/2023","date_ts":1687219200000,"profit_abs":0.0,"wins":0,"draws":0,"loses":0,"winrate":0.0},{"date":"21/06/2023","date_ts":1687305600000,"profit_abs":0.0,"wins":0,"draws":0,"loses":0,"winrate":0.0},{"date":"22/06/2023","date_ts":1687392000000,"profit_abs":0.0,"wins":0,"draws":0,"loses":0,"winrate":0.0},{"date":"23/06/2023","date_ts":1687478400000,"profit_abs":0.0,"wins":0,"draws":0,"loses":0,"winrate":0.0},{"date":"24/06/2023","date_ts":1687564800000,"profit_abs":0.0,"wins":0,"draws":0,"loses":0,"winrate":0.0},{"date":"25/06/2023","date_ts":1687651200000,"profit_abs":0.0,"wins":0,"draws":0,"loses":0,"winrate":0.0},{"date":"26/06/2023","date_ts":1687737600000,"profit_abs":0.0,"wins":0,"draws":0,"loses":0,"winrate":0.0},{"date":"27/06/2023","date_ts":1687824000000,"profit_abs":0.0,"wins":0,"draws":0,"loses":0,"winrate":0.0},{"date":"28/06/2023","date_ts":1687910400000,"profit_abs":0.0,"wins":0,"draws":0,"loses":0,"winrate":0.0},{"date":"29/06/2023","date_ts":1687996800000,"profit_abs":0.0,"wins":0,"draws":0,"loses":0,"winrate":0.0},{"date":"30/06/2023","date_ts":1688083200000,"profit_abs":0.0,"wins":0,"draws":0,"loses":0,"winrate":0.0},{"date":"01/07/2023","date_ts":1688169600000,"profit_abs":0.0,"wins":0,"draws":0,"loses":0,"winrate":0.0},{"date":"02/07/2023","date_ts":1688256000000,"profit_abs":0.0,"wins":0,"draws":0,"loses":0,"winrate":0.0},{"date":"03/07/2023","date_ts":1688342400000,"profit_abs":0.0,"wins":0,"draws":0,"loses":0,"winrate":0.0},{"date":"04/07/2023","date_ts":1688428800000,"profit_abs":0.0,"wins":0,"draws":0,"loses":0,"winrate":0.0},{"date":"05/07/2023","date_ts":1688515200000,"profit_abs":0.0,"wins":0,"draws":0,"loses":0,"winrate":0.0},{"date":"06/07/2023","date_ts":1688601600000,"profit_abs":0.0,"wins":0,"draws":0,"loses":0,"winrate":0.0},{"date":"07/07/2023","date_ts":1688688000000,"profit_abs":0.0,"wins":0,"draws":0,"loses":0,"winrate":0.0},{"date":"08/07/2023","date_ts":1688774400000,"profit_abs":0.0,"wins":0,"draws":0,"loses":0,"winrate":0.0},{"date":"09/07/2023","date_ts":1688860800000,"profit_abs":0.0,"wins":0,"draws":0,"loses":0,"winrate":0.0},{"date":"10/07/2023","date_ts":1688947200000,"profit_abs":0.0,"wins":0,"draws":0,"loses":0,"winrate":0.0},{"date":"11/07/2023","date_ts":1689033600000,"profit_abs":0.0,"wins":0,"draws":0,"loses":0,"winrate":0.0},{"date":"12/07/2023","date_ts":1689120000000,"profit_abs":0.0,"wins":0,"draws":0,"loses":0,"winrate":0.0},{"date":"13/07/2023","date_ts":1689206400000,"profit_abs":0.0,"wins":0,"draws":0,"loses":0,"winrate":0.0},{"date":"14/07/2023","date_ts":1689292800000,"profit_abs":0.0,"wins":0,"draws":0,"loses":0,"winrate":0.0},{"date":"15/07/2023","date_ts":1689379200000,"profit_abs":0.0,"wins":0,"draws":0,"loses":0,"winrate":0.0},{"date":"16/07/2023","date_ts":1689465600000,"profit_abs":0.0,"wins":0,"draws":0,"loses":0,"winrate":0.0},{"date":"17/07/2023","date_ts":1689552000000,"profit_abs":0.0,"wins":0,"draws":0,"loses":0,"winrate":0.0},{"date":"18/07/2023","date_ts":1689638400000,"profit_abs":0.0,"wins":0,"draws":0,"loses":0,"winrate":0.0},{"date":"19/07/2023","date_ts":1689724800000,"profit_abs":0.0,"wins":0,"draws":0,"loses":0,"winrate":0.0},{"date":"20/07/2023","date_ts":1689811200000,"profit_abs":0.0,"wins":0,"draws":0,"loses":0,"winrate":0.0},{"date":"21/07/2023","date_ts":1689897600000,"profit_abs":0.0,"wins":0,"draws":0,"loses":0,"winrate":0.0},{"date":"22/07/2023","date_ts":1689984000000,"profit_abs":0.0,"wins":0,"draws":0,"loses":0,"winrate":0.0},{"date":"23/07/2023","date_ts":1690070400000,"profit_abs":0.0,"wins":0,"draws":0,"loses":0,"winrate":0.0},{"date":"24/07/2023","date_ts":1690156800000,"profit_abs":0.0,"wins":0,"draws":0,"loses":0,"winrate":0.0},{"date":"25/07/2023","date_ts":1690243200000,"profit_abs":0.0,"wins":0,"draws":0,"loses":0,"winrate":0.0},{"date":"26/07/2023","date_ts":1690329600000,"profit_abs":0.0,"wins":0,"draws":0,"loses":0,"winrate":0.0},{"date":"27/07/2023","date_ts":1690416000000,"profit_abs":0.0,"wins":0,"draws":0,"loses":0,"winrate":0.0},{"date":"28/07/2023","date_ts":1690502400000,"profit_abs":0.0,"wins":0,"draws":0,"loses":0,"winrate":0.0},{"date":"29/07/2023","date_ts":1690588800000,"profit_abs":0.0,"wins":0,"draws":0,"loses":0,"winrate":0.0},{"date":"30/07/2023","date_ts":1690675200000,"profit_abs":0.0,"wins":0,"draws":0,"loses":0,"winrate":0.0},{"date":"31/07/2023","date_ts":1690761600000,"profit_abs":0.0,"wins":0,"draws":0,"loses":0,"winrate":0.0},{"date":"01/08/2023","date_ts":1690848000000,"profit_abs":0.0,"wins":0,"draws":0,"loses":0,"winrate":0.0},{"date":"02/08/2023","date_ts":1690934400000,"profit_abs":0.0,"wins":0,"draws":0,"loses":0,"winrate":0.0},{"date":"03/08/2023","date_ts":1691020800000,"profit_abs":0.0,"wins":0,"draws":0,"loses":0,"winrate":0.0},{"date":"04/08/2023","date_ts":1691107200000,"profit_abs":0.0,"wins":0,"draws":0,"loses":0,"winrate":0.0},{"date":"05/08/2023","date_ts":1691193600000,"profit_abs":0.0,"wins":0,"draws":0,"loses":0,"winrate":0.0},{"date":"06/08/2023","date_ts":1691280000000,"profit_abs":0.0,"wins":0,"draws":0,"loses":0,"winrate":0.0},{"date":"07/08/2023","date_ts":1691366400000,"profit_abs":0.0,"wins":0,"draws":0,"loses":0,"winrate":0.0},{"date":"08/08/2023","date_ts":1691452800000,"profit_abs":0.0,"wins":0,"draws":0,"loses":0,"winrate":0.0},{"date":"09/08/2023","date_ts":1691539200000,"profit_abs":0.0,"wins":0,"draws":0,"loses":0,"winrate":0.0},{"date":"10/08/2023","date_ts":1691625600000,"profit_abs":0.0,"wins":0,"draws":0,"loses":0,"winrate":0.0},{"date":"11/08/2023","date_ts":1691712000000,"profit_abs":0.0,"wins":0,"draws":0,"loses":0,"winrate":0.0},{"date":"12/08/2023","date_ts":1691798400000,"profit_abs":0.0,"wins":0,"draws":0,"loses":0,"winrate":0.0},{"date":"13/08/2023","date_ts":1691884800000,"profit_abs":0.0,"wins":0,"draws":0,"loses":0,"winrate":0.0},{"date":"14/08/2023","date_ts":1691971200000,"profit_abs":0.0,"wins":0,"draws":0,"loses":0,"winrate":0.0},{"date":"15/08/2023","date_ts":1692057600000,"profit_abs":0.0,"wins":0,"draws":0,"loses":0,"winrate":0.0},{"date":"16/08/2023","date_ts":1692144000000,"profit_abs":0.0,"wins":0,"draws":0,"loses":0,"winrate":0.0},{"date":"17/08/2023","date_ts":1692230400000,"profit_abs":5.98850406,"wins":1,"draws":0,"loses":0,"winrate":1.0}],"week":[{"date":"23/01/2023","date_ts":1674432000000,"profit_abs":3.34107364,"wins":1,"draws":0,"loses":0,"winrate":1.0},{"date":"30/01/2023","date_ts":1675036800000,"profit_abs":0.0,"wins":0,"draws":0,"loses":0,"winrate":0.0},{"date":"06/02/2023","date_ts":1675641600000,"profit_abs":0.0,"wins":0,"draws":0,"loses":0,"winrate":0.0},{"date":"13/02/2023","date_ts":1676246400000,"profit_abs":0.0,"wins":0,"draws":0,"loses":0,"winrate":0.0},{"date":"20/02/2023","date_ts":1676851200000,"profit_abs":0.0,"wins":0,"draws":0,"loses":0,"winrate":0.0},{"date":"27/02/2023","date_ts":1677456000000,"profit_abs":0.0,"wins":0,"draws":0,"loses":0,"winrate":0.0},{"date":"06/03/2023","date_ts":1678060800000,"profit_abs":0.71137739,"wins":1,"draws":0,"loses":0,"winrate":1.0},{"date":"13/03/2023","date_ts":1678665600000,"profit_abs":2.60195182,"wins":1,"draws":0,"loses":0,"winrate":1.0},{"date":"20/03/2023","date_ts":1679270400000,"profit_abs":0.0,"wins":0,"draws":0,"loses":0,"winrate":0.0},{"date":"27/03/2023","date_ts":1679875200000,"profit_abs":0.0,"wins":0,"draws":0,"loses":0,"winrate":0.0},{"date":"03/04/2023","date_ts":1680480000000,"profit_abs":0.0,"wins":0,"draws":0,"loses":0,"winrate":0.0},{"date":"10/04/2023","date_ts":1681084800000,"profit_abs":0.0,"wins":0,"draws":0,"loses":0,"winrate":0.0},{"date":"17/04/2023","date_ts":1681689600000,"profit_abs":0.0,"wins":0,"draws":0,"loses":0,"winrate":0.0},{"date":"24/04/2023","date_ts":1682294400000,"profit_abs":0.0,"wins":0,"draws":1,"loses":0,"winrate":0.0},{"date":"01/05/2023","date_ts":1682899200000,"profit_abs":1.83232413,"wins":1,"draws":0,"loses":0,"winrate":1.0},{"date":"08/05/2023","date_ts":1683504000000,"profit_abs":0.0,"wins":0,"draws":0,"loses":0,"winrate":0.0},{"date":"15/05/2023","date_ts":1684108800000,"profit_abs":0.0,"wins":0,"draws":0,"loses":0,"winrate":0.0},{"date":"22/05/2023","date_ts":1684713600000,"profit_abs":0.0,"wins":0,"draws":0,"loses":0,"winrate":0.0},{"date":"29/05/2023","date_ts":1685318400000,"profit_abs":0.0,"wins":0,"draws":0,"loses":0,"winrate":0.0},{"date":"05/06/2023","date_ts":1685923200000,"profit_abs":0.0,"wins":0,"draws":0,"loses":0,"winrate":0.0},{"date":"12/06/2023","date_ts":1686528000000,"profit_abs":0.0,"wins":0,"draws":0,"loses":0,"winrate":0.0},{"date":"19/06/2023","date_ts":1687132800000,"profit_abs":0.15110341,"wins":1,"draws":0,"loses":0,"winrate":1.0},{"date":"26/06/2023","date_ts":1687737600000,"profit_abs":0.0,"wins":0,"draws":0,"loses":0,"winrate":0.0},{"date":"03/07/2023","date_ts":1688342400000,"profit_abs":0.0,"wins":0,"draws":0,"loses":0,"winrate":0.0},{"date":"10/07/2023","date_ts":1688947200000,"profit_abs":0.0,"wins":0,"draws":0,"loses":0,"winrate":0.0},{"date":"17/07/2023","date_ts":1689552000000,"profit_abs":0.0,"wins":0,"draws":0,"loses":0,"winrate":0.0},{"date":"24/07/2023","date_ts":1690156800000,"profit_abs":0.0,"wins":0,"draws":0,"loses":0,"winrate":0.0},{"date":"31/07/2023","date_ts":1690761600000,"profit_abs":0.0,"wins":0,"draws":0,"loses":0,"winrate":0.0},{"date":"07/08/2023","date_ts":1691366400000,"profit_abs":0.0,"wins":0,"draws":0,"loses":0,"winrate":0.0},{"date":"14/08/2023","date_ts":1691971200000,"profit_abs":0.0,"wins":0,"draws":0,"loses":0,"winrate":0.0},{"date":"21/08/2023","date_ts":1692576000000,"profit_abs":5.98850406,"wins":1,"draws":0,"loses":0,"winrate":1.0}],"month":[{"date":"31/01/2023","date_ts":1675123200000,"profit_abs":3.34107364,"wins":1,"draws":0,"loses":0,"winrate":1.0},{"date":"28/02/2023","date_ts":1677542400000,"profit_abs":0.0,"wins":0,"draws":0,"loses":0,"winrate":0.0},{"date":"31/03/2023","date_ts":1680220800000,"profit_abs":3.31332921,"wins":2,"draws":0,"loses":0,"winrate":1.0},{"date":"30/04/2023","date_ts":1682812800000,"profit_abs":1.83232413,"wins":1,"draws":1,"loses":0,"winrate":0.5},{"date":"31/05/2023","date_ts":1685491200000,"profit_abs":0.0,"wins":0,"draws":0,"loses":0,"winrate":0.0},{"date":"30/06/2023","date_ts":1688083200000,"profit_abs":0.15110341,"wins":1,"draws":0,"loses":0,"winrate":1.0},{"date":"31/07/2023","date_ts":1690761600000,"profit_abs":0.0,"wins":0,"draws":0,"loses":0,"winrate":0.0},{"date":"31/08/2023","date_ts":1693440000000,"profit_abs":5.98850406,"wins":1,"draws":0,"loses":0,"winrate":1.0}]},"backtest_best_day":0.029970029970029975,"backtest_worst_day":0.0,"backtest_best_day_abs":5.98850406,"backtest_worst_day_abs":0.0,"winning_days":6,"draw_days":206,"losing_days":0,"daily_profit":[["2023-01-18",3.34107364],["2023-01-19",0.0],["2023-01-20",0.0],["2023-01-21",0.0],["2023-01-22",0.0],["2023-01-23",0.0],["2023-01-24",0.0],["2023-01-25",0.0],["2023-01-26",0.0],["2023-01-27",0.0],["2023-01-28",0.0],["2023-01-29",0.0],["2023-01-30",0.0],["2023-01-31",0.0],["2023-02-01",0.0],["2023-02-02",0.0],["2023-02-03",0.0],["2023-02-04",0.0],["2023-02-05",0.0],["2023-02-06",0.0],["2023-02-07",0.0],["2023-02-08",0.0],["2023-02-09",0.0],["2023-02-10",0.0],["2023-02-11",0.0],["2023-02-12",0.0],["2023-02-13",0.0],["2023-02-14",0.0],["2023-02-15",0.0],["2023-02-16",0.0],["2023-02-17",0.0],["2023-02-18",0.0],["2023-02-19",0.0],["2023-02-20",0.0],["2023-02-21",0.0],["2023-02-22",0.0],["2023-02-23",0.0],["2023-02-24",0.0],["2023-02-25",0.0],["2023-02-26",0.0],["2023-02-27",0.0],["2023-02-28",0.0],["2023-03-01",0.0],["2023-03-02",0.0],["2023-03-03",0.71137739],["2023-03-04",0.0],["2023-03-05",0.0],["2023-03-06",0.0],["2023-03-07",0.0],["2023-03-08",0.0],["2023-03-09",2.60195182],["2023-03-10",0.0],["2023-03-11",0.0],["2023-03-12",0.0],["2023-03-13",0.0],["2023-03-14",0.0],["2023-03-15",0.0],["2023-03-16",0.0],["2023-03-17",0.0],["2023-03-18",0.0],["2023-03-19",0.0],["2023-03-20",0.0],["2023-03-21",0.0],["2023-03-22",0.0],["2023-03-23",0.0],["2023-03-24",0.0],["2023-03-25",0.0],["2023-03-26",0.0],["2023-03-27",0.0],["2023-03-28",0.0],["2023-03-29",0.0],["2023-03-30",0.0],["2023-03-31",0.0],["2023-04-01",0.0],["2023-04-02",0.0],["2023-04-03",0.0],["2023-04-04",0.0],["2023-04-05",0.0],["2023-04-06",0.0],["2023-04-07",0.0],["2023-04-08",0.0],["2023-04-09",0.0],["2023-04-10",0.0],["2023-04-11",0.0],["2023-04-12",0.0],["2023-04-13",0.0],["2023-04-14",0.0],["2023-04-15",0.0],["2023-04-16",0.0],["2023-04-17",0.0],["2023-04-18",0.0],["2023-04-19",0.0],["2023-04-20",0.0],["2023-04-21",0.0],["2023-04-22",0.0],["2023-04-23",0.0],["2023-04-24",0.0],["2023-04-25",0.0],["2023-04-26",1.83232413],["2023-04-27",0.0],["2023-04-28",0.0],["2023-04-29",0.0],["2023-04-30",0.0],["2023-05-01",0.0],["2023-05-02",0.0],["2023-05-03",0.0],["2023-05-04",0.0],["2023-05-05",0.0],["2023-05-06",0.0],["2023-05-07",0.0],["2023-05-08",0.0],["2023-05-09",0.0],["2023-05-10",0.0],["2023-05-11",0.0],["2023-05-12",0.0],["2023-05-13",0.0],["2023-05-14",0.0],["2023-05-15",0.0],["2023-05-16",0.0],["2023-05-17",0.0],["2023-05-18",0.0],["2023-05-19",0.0],["2023-05-20",0.0],["2023-05-21",0.0],["2023-05-22",0.0],["2023-05-23",0.0],["2023-05-24",0.0],["2023-05-25",0.0],["2023-05-26",0.0],["2023-05-27",0.0],["2023-05-28",0.0],["2023-05-29",0.0],["2023-05-30",0.0],["2023-05-31",0.0],["2023-06-01",0.0],["2023-06-02",0.0],["2023-06-03",0.0],["2023-06-04",0.0],["2023-06-05",0.0],["2023-06-06",0.0],["2023-06-07",0.0],["2023-06-08",0.0],["2023-06-09",0.0],["2023-06-10",0.0],["2023-06-11",0.0],["2023-06-12",0.0],["2023-06-13",0.0],["2023-06-14",0.15110341],["2023-06-15",0.0],["2023-06-16",0.0],["2023-06-17",0.0],["2023-06-18",0.0],["2023-06-19",0.0],["2023-06-20",0.0],["2023-06-21",0.0],["2023-06-22",0.0],["2023-06-23",0.0],["2023-06-24",0.0],["2023-06-25",0.0],["2023-06-26",0.0],["2023-06-27",0.0],["2023-06-28",0.0],["2023-06-29",0.0],["2023-06-30",0.0],["2023-07-01",0.0],["2023-07-02",0.0],["2023-07-03",0.0],["2023-07-04",0.0],["2023-07-05",0.0],["2023-07-06",0.0],["2023-07-07",0.0],["2023-07-08",0.0],["2023-07-09",0.0],["2023-07-10",0.0],["2023-07-11",0.0],["2023-07-12",0.0],["2023-07-13",0.0],["2023-07-14",0.0],["2023-07-15",0.0],["2023-07-16",0.0],["2023-07-17",0.0],["2023-07-18",0.0],["2023-07-19",0.0],["2023-07-20",0.0],["2023-07-21",0.0],["2023-07-22",0.0],["2023-07-23",0.0],["2023-07-24",0.0],["2023-07-25",0.0],["2023-07-26",0.0],["2023-07-27",0.0],["2023-07-28",0.0],["2023-07-29",0.0],["2023-07-30",0.0],["2023-07-31",0.0],["2023-08-01",0.0],["2023-08-02",0.0],["2023-08-03",0.0],["2023-08-04",0.0],["2023-08-05",0.0],["2023-08-06",0.0],["2023-08-07",0.0],["2023-08-08",0.0],["2023-08-09",0.0],["2023-08-10",0.0],["2023-08-11",0.0],["2023-08-12",0.0],["2023-08-13",0.0],["2023-08-14",0.0],["2023-08-15",0.0],["2023-08-16",0.0],["2023-08-17",5.98850406]],"wins":6,"losses":0,"draws":1,"winrate":0.8571428571428571,"holding_avg":"2:51:00","holding_avg_s":10260.0,"winner_holding_avg":"2:28:00","winner_holding_avg_s":8880.0,"loser_holding_avg":"0:00:00","loser_holding_avg_s":0.0,"max_consecutive_wins":3,"max_consecutive_losses":1,"max_drawdown":0.0,"max_drawdown_account":0.0,"max_relative_drawdown":0.0,"max_drawdown_abs":0.0,"max_drawdown_low":0.0,"max_drawdown_high":0.0,"drawdown_start":"1970-01-01 00:00:00+00:00","drawdown_start_ts":0,"drawdown_end":"1970-01-01 00:00:00+00:00","drawdown_end_ts":0,"csum_min":0,"csum_max":0}},"strategy_comparison":[{"key":"UniversalMACD","trades":7,"profit_mean":0.010491077876856289,"profit_mean_pct":1.049107787685629,"profit_sum":0.07343754513799403,"profit_sum_pct":7.34,"profit_total_abs":14.62633445,"profit_total":0.01462633445,"profit_total_pct":1.46,"duration_avg":"2:51:00","wins":6,"draws":1,"losses":0,"winrate":0.8571428571428571,"max_drawdown_account":0.0,"max_drawdown_abs":"0"}]}